{
    "@context": [
        "http://www.w3.org/ns/csvw",
        {
            "@language": "en"
        }
    ],
    "dc:conformsTo": "http://cldf.clld.org/v1.0/terms.rdf#Wordlist",
    "dc:contributor": [
        "https://github.com/Anaphory/lexedata/blob/master/src/lexedata/edit/add_metadata.py"
    ],
    "dc:source": "sources.bib",
    "dialect": {
        "commentPrefix": null
    },
    "tables": [
        {
            "dc:conformsTo": "http://cldf.clld.org/v1.0/terms.rdf#FormTable",
            "dc:extent": 8767,
            "tableSchema": {
                "columns": [
                    {
                        "datatype": {
                            "base": "string",
                            "format": "[a-zA-Z0-9_\\-]+"
                        },
                        "propertyUrl": "http://cldf.clld.org/v1.0/terms.rdf#id",
                        "required": true,
                        "name": "ID"
                    },
                    {
                        "datatype": "string",
                        "propertyUrl": "http://cldf.clld.org/v1.0/terms.rdf#languageReference",
                        "required": true,
                        "name": "Language_ID"
                    },
                    {
                        "datatype": "string",
                        "propertyUrl": "http://cldf.clld.org/v1.0/terms.rdf#parameterReference",
                        "required": true,
                        "name": "Parameter_ID"
                    },
                    {
                        "datatype": "string",
                        "propertyUrl": "http://cldf.clld.org/v1.0/terms.rdf#form",
                        "required": true,
                        "name": "Form"
                    },
                    {
                        "datatype": "string",
                        "separator": "~",
                        "name": "Variants"
                    },
                    {
                        "datatype": "string",
                        "propertyUrl": "http://cldf.clld.org/v1.0/terms.rdf#comment",
                        "required": false,
                        "name": "Comment"
                    },
                    {
                        "datatype": "string",
                        "name": "Plural"
                    },
                    {
                        "datatype": "string",
                        "propertyUrl": "http://cldf.clld.org/v1.0/terms.rdf#source",
                        "required": false,
                        "separator": ";",
                        "name": "Source"
                    },
                    {
                        "datatype": "string",
                        "name": "Translation"
                    },
                    {
                        "datatype": "string",
                        "propertyUrl": "http://cldf.clld.org/v1.0/terms.rdf#segments",
                        "required": false,
                        "separator": " ",
                        "name": "Segments"
                    }
                ],
                "foreignKeys": [
                    {
                        "columnReference": [
                            "Language_ID"
                        ],
                        "reference": {
                            "resource": "languages.csv",
                            "columnReference": [
                                "Language_ID"
                            ]
                        }
                    }
                ],
                "primaryKey": [
                    "ID"
                ]
            },
            "url": "forms.csv"
        },
        {
            "dc:conformsTo": "http://cldf.clld.org/v1.0/terms.rdf#LanguageTable",
            "dc:extent": 84,
            "tableSchema": {
                "columns": [
                    {
                        "datatype": "string",
                        "propertyUrl": "http://cldf.clld.org/v1.0/terms.rdf#name",
                        "required": true,
                        "name": "Language"
                    },
                    {
                        "datatype": "string",
                        "name": "Glottolog_Name"
                    },
                    {
                        "datatype": "string",
                        "propertyUrl": "http://cldf.clld.org/v1.0/terms.rdf#glottocode",
                        "name": "Glottocode"
                    },
                    {
                        "datatype": "string",
                        "name": "Guthrie_Code"
                    },
                    {
                        "datatype": "string",
                        "name": "ISO_Code"
                    },
                    {
                        "datatype": "string",
                        "propertyUrl": "http://cldf.clld.org/v1.0/terms.rdf#comment",
                        "name": "comment"
                    },
                    {
                        "datatype": "string",
                        "propertyUrl": "http://cldf.clld.org/v1.0/terms.rdf#id",
                        "required": true,
                        "name": "Language_ID"
                    }
                ],
                "primaryKey": [
                    "Language_ID"
                ]
            },
            "url": "languages.csv"
        },
        {
            "dc:conformsTo": "http://cldf.clld.org/v1.0/terms.rdf#CognatesetTable",
            "dc:extent": 21724,
            "tableSchema": {
                "columns": [
                    {
                        "datatype": "string",
                        "propertyUrl": "http://cldf.clld.org/v1.0/terms.rdf#id",
                        "required": true,
                        "name": "Cognateset_ID"
                    },
                    {
                        "datatype": "string",
                        "propertyUrl": "http://cldf.clld.org/v1.0/terms.rdf#comment",
                        "name": "Comment"
                    },
                    {
                        "datatype": "string",
                        "propertyUrl": "http://cldf.clld.org/v1.0/terms.rdf#name",
                        "name": "Cognateset_Name"
                    }
                ],
                "primaryKey": [
                    "Cognateset_ID"
                ]
            },
            "url": "cognatesets.csv"
        },
        {
            "dc:conformsTo": "http://cldf.clld.org/v1.0/terms.rdf#CognateTable",
            "dc:extent": 41315,
            "tableSchema": {
                "columns": [
                    {
                        "datatype": "string",
                        "propertyUrl": "http://cldf.clld.org/v1.0/terms.rdf#id",
                        "required": true,
                        "name": "Cognate_ID"
                    },
                    {
                        "datatype": "string",
                        "propertyUrl": "http://cldf.clld.org/v1.0/terms.rdf#formReference",
                        "required": true,
                        "name": "Form_ID"
                    },
                    {
                        "datatype": "string",
                        "propertyUrl": "http://cldf.clld.org/v1.0/terms.rdf#cognatesetReference",
                        "required": true,
                        "name": "Cognateset_ID"
                    },
                    {
                        "datatype": "string",
                        "propertyUrl": "http://cldf.clld.org/v1.0/terms.rdf#comment",
                        "name": "Comment"
                    }
                ],
                "foreignKeys": [
                    {
                        "columnReference": [
                            "Form_ID"
                        ],
                        "reference": {
                            "resource": "forms.csv",
                            "columnReference": [
                                "ID"
                            ]
                        }
                    },
                    {
                        "columnReference": [
                            "Cognateset_ID"
                        ],
                        "reference": {
                            "resource": "cognatesets.csv",
                            "columnReference": [
                                "Cognateset_ID"
                            ]
                        }
                    }
                ],
                "primaryKey": [
                    "Cognate_ID"
                ]
            },
            "url": "cognates.csv"
        }
    ]
}